digital_object/__init__.py
digital_object/common.py
digital_object/digital_object_model.py
digital_object/digital_object_util.py
digital_object/filter.py
digital_object/format_alto_v3_util.py
digital_object/format_page_util.py
digital_object/main.py
digital_object/minidom_util.py
digital_object-0.2.0.dist-info/LICENSE
digital_object-0.2.0.dist-info/METADATA
digital_object-0.2.0.dist-info/WHEEL
digital_object-0.2.0.dist-info/RECORD
