Metadata-Version: 2.1
Name: digital-object
Version: 0.2.0
Summary: digital object assets
Home-page: https://github.com/ulb-sachsen-anhalt/digitized-object
License: MIT
Keywords: digitization,digital object,digitized content,ocr
Author: Universitäts- und Landesbibliothek Sachsen-Anhalt
Author-email: development@bibliothek.uni-halle.de
Maintainer: Uwe Hartwig
Maintainer-email: uwe.hartwig@bibliothek.uni-halle.de
Requires-Python: >=3.8,<4.0
Classifier: License :: OSI Approved :: MIT License
Classifier: Operating System :: OS Independent
Classifier: Programming Language :: Python :: 3
Classifier: Programming Language :: Python :: 3.8
Classifier: Programming Language :: Python :: 3.9
Classifier: Programming Language :: Python :: 3.10
Classifier: Programming Language :: Python :: 3.11
Requires-Dist: shapely (>=2.0.1,<3.0.0)
Project-URL: Repository, https://github.com/ulb-sachsen-anhalt/digitized-object
